sodius2/__init__.py
sodius2/cli_wrapper.py
sodius2-0.1.4.dist-info/METADATA
sodius2-0.1.4.dist-info/WHEEL
sodius2-0.1.4.dist-info/entry_points.txt
sodius2-0.1.4.dist-info/top_level.txt
sodius2-0.1.4.dist-info/RECORD
